snippet_chest/__init__.py
snippet_chest/matplotlib.py
snippet_chest/requests.py
snippet_chest-0.0.1.dist-info/METADATA
snippet_chest-0.0.1.dist-info/WHEEL
snippet_chest-0.0.1.dist-info/top_level.txt
snippet_chest-0.0.1.dist-info/RECORD
